{
  "allSongs": [
    {
      "id": 1,
      "songName": "Blinding Lights",
      "releaseDate": "29/11/2019",
      "imageURL": "",
      "ratings": [5,4.5,3.5,5],
      "artists": [
        "The Weekend"
      ]
    },
    {
      "id": 2,
      "songName": "God's Plan",
      "releaseDate": "19/01/2018",
      "imageURL": "",
      "ratings": [4,4,3.5,3,5],
      "artists": [
        "Drake"
      ]
    },
    {
      "id": 3,
      "songName": "Old Skool",
      "releaseDate": "27/03/2020",
      "imageURL": "",
      "ratings": [5,4,5,3,2.5],
      "artists": [
        "Sidhu Moosewala"
      ]
    },
    {
      "id": 4,
      "songName": "Kamikaze",
      "releaseDate": "31/08/2018",
      "imageURL": "",
      "ratings": [3,3,4,4],
      "artists": [
        "Marshal Mathers"
      ]
    }
  ]
}